README.rst
setup.py
scripts/get_trilegal
starutils/__init__.py
starutils/constraints.py
starutils/contrastcurve.py
starutils/extinction.py
starutils/populations.py
starutils/trilegal.py
starutils/utils.py
starutils.egg-info/PKG-INFO
starutils.egg-info/SOURCES.txt
starutils.egg-info/dependency_links.txt
starutils.egg-info/not-zip-safe
starutils.egg-info/requires.txt
starutils.egg-info/top_level.txt
starutils/data/extinction.txt
starutils/data/multiple_pecc.txt
starutils/data/raghavan_periods.dat
starutils/tests/__init__.py
starutils/tests/test_populations.py