Metadata-Version: 1.1
Name: starutils
Version: 0.3
Summary: Useful things for playing with simulated star populations.
Home-page: https://github.com/timothydmorton/starutils
Author: Timothy D. Morton
Author-email: tim.morton@gmail.com
License: UNKNOWN
Platform: UNKNOWN
Classifier: Development Status :: 3 - Alpha
Classifier: Intended Audience :: Science/Research
Classifier: Operating System :: OS Independent
Classifier: Programming Language :: Python
Classifier: Topic :: Scientific/Engineering
Classifier: Topic :: Scientific/Engineering :: Astronomy
